abcddb2vcard/ABCDDB.py
abcddb2vcard/__init__.py
abcddb2vcard/__main__.py
abcddb2vcard/abcddb2vcard.py
abcddb2vcard/vcard2img.py
abcddb2vcard-1.2.2.dist-info/LICENSE
abcddb2vcard-1.2.2.dist-info/METADATA
abcddb2vcard-1.2.2.dist-info/WHEEL
abcddb2vcard-1.2.2.dist-info/entry_points.txt
abcddb2vcard-1.2.2.dist-info/top_level.txt
abcddb2vcard-1.2.2.dist-info/RECORD
