Metadata-Version: 2.1
Name: abcddb2vcard
Version: 1.2.2
Summary: Convert AddressBook database (.abcddb) to Contacts VCards file (.vcf)
Home-page: https://github.com/relikd/abcddb2vcard
Author: relikd
License: MIT
Keywords: abcddb,abcd,address book,vcard,contacts,converter,export,backup
Platform: UNKNOWN
Classifier: Development Status :: 5 - Production/Stable
Classifier: Environment :: Console
Classifier: Environment :: MacOS X
Classifier: License :: OSI Approved :: MIT License
Classifier: Operating System :: OS Independent
Classifier: Programming Language :: Python
Classifier: Programming Language :: Python :: 3
Classifier: Programming Language :: Python :: 3 :: Only
Classifier: Programming Language :: Python :: 3.6
Classifier: Programming Language :: Python :: 3.7
Classifier: Programming Language :: Python :: 3.8
Classifier: Programming Language :: Python :: 3.9
Classifier: Programming Language :: Python :: 3.10
Classifier: Programming Language :: SQL
Classifier: Topic :: Communications :: Email :: Address Book
Classifier: Topic :: Software Development :: Libraries :: Python Modules
Classifier: Topic :: System :: Archiving :: Backup
Classifier: Topic :: Utilities
Requires-Python: >=3.6
License-File: LICENSE
